{
  "id": "0000-51467dd",
  "pr": 0,
  "title": "polaris-pipeline-check",
  "url": "https://github.com/gittensor-ai-lab/sparkinfer/pull/0",
  "commit": "51467dd",
  "label": "none",
  "tps": 385.58,
  "baseline_tps": 385.82,
  "delta_pct": -0.1,
  "delta_tps": -0.24,
  "top1": 0.9471,
  "kl": 0.0246,
  "gpu": "RTX 5090 (sm_120) \u00b7 vast.ai",
  "date": "2026-07-10",
  "frontier": 385.82,
  "eval_mode": "longctx",
  "score_context": 16384,
  "best_context_label": "16k-context",
  "context_gains_pct": {
    "128-context": -0.21,
    "512-context": -0.22,
    "4k-context": -0.18,
    "16k-context": -0.06,
    "32k-context": -0.07
  },
  "regression_labels": [],
  "auto_close": null,
  "ctx_128_tps": 425.8,
  "ctx_512_tps": 419.11,
  "ctx_2048_tps": null,
  "ctx_4096_tps": 402.42,
  "ctx_16384_tps": 385.58,
  "ctx_32768_tps": 363.58,
  "guard_128_baseline": 426.68,
  "guard_128_ratio": 0.9979,
  "guard_128_pass": true,
  "guard_512_baseline": 420.04,
  "guard_512_ratio": 0.9978,
  "guard_512_pass": true,
  "guard_4k_baseline": 403.15,
  "guard_4k_ratio": 0.9982,
  "guard_4k_pass": true,
  "guard_16k_baseline": 385.82,
  "guard_16k_ratio": 0.9994,
  "guard_16k_pass": true,
  "guard_32k_baseline": 363.84,
  "guard_32k_ratio": 0.9993,
  "guard_32k_pass": true,
  "guard_2k_baseline": null,
  "guard_2k_ratio": null,
  "guard_2k_pass": null,
  "clocks_pinned": false,
  "clock_mhz": "0",
  "clock_spread_mhz": "0",
  "eval_seed": "e5a1b80c5c273143",
  "model_sha_pinned": true,
  "llama_commit": "6f4f53f2b7da54fcdbbecaaa734337c337ad6176",
  "polaris": true,
  "polaris_receipt_id": "8dd8d6f26031092a61e8d481f3046117"
}